[{"image": "008-S1-B010.png", "annotations": [{"label": "ID", "coordinates": {"x": 2117.0, "y": 227.0, "width": 271.0, "height": 51.0}, "extra_label": "008-S1-B010"}, {"label": "printed_text", "coordinates": {"x": 171.0, "y": 291.0, "width": 2228.0, "height": 258.0}, "extra_label": ""}, {"label": "handwritten_text", "coordinates": {"x": 169.0, "y": 574.0, "width": 2379.0, "height": 1239.0}, "extra_label": ""}, {"label": "line", "coordinates": {"x": 230.32432432432432, "y": 588.3513513513514, "width": 2182.0, "height": 127.0}, "extra_label": "Trust|Investing|y|otras|,|solo|triunfan|en"}, {"label": "word", "coordinates": {"x": 274.0, "y": 606.0, "width": 285.0, "height": 107.0}, "extra_label": "Trust"}, {"label": "word", "coordinates": {"x": 587.0, "y": 606.0, "width": 470.0, "height": 129.0}, "extra_label": "Investing"}, {"label": "word", "coordinates": {"x": 1106.0, "y": 662.0, "width": 48.0, "height": 73.0}, "extra_label": "y"}, {"label": "word", "coordinates": {"x": 1199.0, "y": 606.0, "width": 218.32432432432438, "height": 117.35135135135135}, "extra_label": "otras"}, {"label": "word", "coordinates": {"x": 1398.3243243243244, "y": 675.3513513513514, "width": 49.0, "height": 54.0}, "extra_label": ","}, {"label": "word", "coordinates": {"x": 1461.0, "y": 606.0, "width": 221.0, "height": 129.0}, "extra_label": "solo"}, {"label": "word", "coordinates": {"x": 1709.0, "y": 606.0, "width": 456.0, "height": 129.0}, "extra_label": "triunfan"}, {"label": "word", "coordinates": {"x": 2220.0, "y": 655.0, "width": 162.0, "height": 50.0}, "extra_label": "en"}, {"label": "line", "coordinates": {"x": 255.32432432432432, "y": 721.3513513513514, "width": 2184.0, "height": 122.64864864864865}, "extra_label": "pa\u00edses|como|Cuba|,|d\u00f3nde|miles|de|personas"}, {"label": "word", "coordinates": {"x": 288.0, "y": 735.0, "width": 311.0, "height": 109.0}, "extra_label": "pa\u00edses"}, {"label": "word", "coordinates": {"x": 658.0, "y": 766.0, "width": 250.0, "height": 78.0}, "extra_label": "como"}, {"label": "word", "coordinates": {"x": 941.0, "y": 735.0, "width": 249.32432432432438, "height": 105.35135135135135}, "extra_label": "Cuba"}, {"label": "word", "coordinates": {"x": 1198.3243243243244, "y": 783.3513513513514, "width": 27.0, "height": 54.0}, "extra_label": ","}, {"label": "word", "coordinates": {"x": 1249.3243243243244, "y": 726.3513513513514, "width": 322.0, "height": 86.64864864864865}, "extra_label": "d\u00f3nde"}, {"label": "word", "coordinates": {"x": 1595.0, "y": 735.0, "width": 278.0, "height": 85.0}, "extra_label": "miles"}, {"label": "word", "coordinates": {"x": 1903.3243243243244, "y": 734.3513513513514, "width": 131.35135135135124, "height": 65.64864864864865}, "extra_label": "de"}, {"label": "word", "coordinates": {"x": 2041.0, "y": 735.0, "width": 368.0, "height": 109.0}, "extra_label": "personas"}, {"label": "line", "coordinates": {"x": 249.32432432432432, "y": 837.3513513513514, "width": 2239.3513513513517, "height": 116.0}, "extra_label": "est\u00e1n|\u00e1vidos|de|ganar|sin|trabajar|.|Conoz|-"}, {"label": "word", "coordinates": {"x": 285.0, "y": 850.3513513513514, "width": 309.6756756756756, "height": 92.64864864864865}, "extra_label": "est\u00e1n"}, {"label": "word", "coordinates": {"x": 643.0, "y": 844.0, "width": 336.0, "height": 109.0}, "extra_label": "\u00e1vidos"}, {"label": "word", "coordinates": {"x": 1001.0, "y": 844.0, "width": 127.0, "height": 78.0}, "extra_label": "de"}, {"label": "word", "coordinates": {"x": 1200.0, "y": 844.0, "width": 307.0, "height": 125.0}, "extra_label": "ganar"}, {"label": "word", "coordinates": {"x": 1520.0, "y": 844.0, "width": 208.32432432432438, "height": 87.35135135135135}, "extra_label": "sin"}, {"label": "word", "coordinates": {"x": 1739.3243243243244, "y": 848.3513513513514, "width": 380.9999999999998, "height": 132.0}, "extra_label": "trabajar"}, {"label": "word", "coordinates": {"x": 2130.324324324324, "y": 902.3513513513514, "width": 30.0, "height": 43.0}, "extra_label": "."}, {"label": "word", "coordinates": {"x": 2201.0, "y": 844.0, "width": 202.32432432432415, "height": 120.35135135135135}, "extra_label": "Conoz"}, {"label": "word", "coordinates": {"x": 2420.324324324324, "y": 867.3513513513514, "width": 35.0, "height": 27.0}, "extra_label": "-"}, {"label": "line", "coordinates": {"x": 316.0, "y": 958.3513513513514, "width": 2124.675675675676, "height": 131.64864864864865}, "extra_label": "co|cubanos|en|pa\u00edses|desarrollados|de|-"}, {"label": "word", "coordinates": {"x": 326.0, "y": 999.0, "width": 94.0, "height": 91.0}, "extra_label": "co"}, {"label": "word", "coordinates": {"x": 500.0, "y": 969.0, "width": 404.0, "height": 106.0}, "extra_label": "cubanos"}, {"label": "word", "coordinates": {"x": 937.0, "y": 992.0, "width": 158.0, "height": 73.0}, "extra_label": "en"}, {"label": "word", "coordinates": {"x": 1143.0, "y": 959.3513513513514, "width": 310.6756756756756, "height": 109.99999999999989}, "extra_label": "pa\u00edses"}, {"label": "word", "coordinates": {"x": 1483.6756756756756, "y": 964.3513513513514, "width": 617.3243243243244, "height": 102.99999999999989}, "extra_label": "desarrollados"}, {"label": "word", "coordinates": {"x": 2182.0, "y": 969.0, "width": 120.0, "height": 67.0}, "extra_label": "de"}, {"label": "word", "coordinates": {"x": 2376.324324324324, "y": 977.3513513513514, "width": 57.0, "height": 36.0}, "extra_label": "-"}, {"label": "line", "coordinates": {"x": 330.0, "y": 1075.3513513513512, "width": 2172.675675675676, "height": 127.0}, "extra_label": "Europa|que|ni|siquiera|intentan|en|-"}, {"label": "word", "coordinates": {"x": 340.0, "y": 1090.0, "width": 397.0, "height": 112.0}, "extra_label": "Europa"}, {"label": "word", "coordinates": {"x": 813.0, "y": 1115.0, "width": 198.0, "height": 87.0}, "extra_label": "que"}, {"label": "word", "coordinates": {"x": 1061.0, "y": 1096.3513513513512, "width": 140.32432432432438, "height": 81.64864864864876}, "extra_label": "ni"}, {"label": "word", "coordinates": {"x": 1234.0, "y": 1090.0, "width": 460.0, "height": 112.0}, "extra_label": "siquiera"}, {"label": "word", "coordinates": {"x": 1735.0, "y": 1083.3513513513512, "width": 480.67567567567585, "height": 93.64864864864876}, "extra_label": "intentan"}, {"label": "word", "coordinates": {"x": 2259.0, "y": 1090.0, "width": 153.32432432432415, "height": 63.35135135135124}, "extra_label": "en"}, {"label": "word", "coordinates": {"x": 2428.324324324324, "y": 1107.3513513513512, "width": 40.0, "height": 33.0}, "extra_label": "-"}, {"label": "line", "coordinates": {"x": 336.0, "y": 1202.0, "width": 2132.0, "height": 117.0}, "extra_label": "tender|el|sistema|de|la|empresa|,|sen|-"}, {"label": "word", "coordinates": {"x": 366.3243243243243, "y": 1221.3513513513512, "width": 331.99999999999994, "height": 97.64864864864876}, "extra_label": "tender"}, {"label": "word", "coordinates": {"x": 752.0, "y": 1202.0, "width": 143.0, "height": 117.0}, "extra_label": "el"}, {"label": "word", "coordinates": {"x": 945.0, "y": 1202.0, "width": 490.0, "height": 117.0}, "extra_label": "sistema"}, {"label": "word", "coordinates": {"x": 1459.0, "y": 1202.0, "width": 122.0, "height": 83.0}, "extra_label": "de"}, {"label": "word", "coordinates": {"x": 1599.0, "y": 1202.0, "width": 194.32432432432438, "height": 81.35135135135124}, "extra_label": "la"}, {"label": "word", "coordinates": {"x": 1803.3243243243244, "y": 1213.3513513513512, "width": 402.9999999999998, "height": 105.0}, "extra_label": "empresa"}, {"label": "word", "coordinates": {"x": 2195.324324324324, "y": 1248.3513513513512, "width": 68.0, "height": 48.0}, "extra_label": ","}, {"label": "word", "coordinates": {"x": 2271.0, "y": 1206.0, "width": 146.32432432432415, "height": 78.35135135135124}, "extra_label": "sen"}, {"label": "word", "coordinates": {"x": 2428.324324324324, "y": 1231.3513513513512, "width": 29.0, "height": 38.0}, "extra_label": "-"}, {"label": "line", "coordinates": {"x": 366.0, "y": 1319.0, "width": 2094.324324324324, "height": 104.35135135135124}, "extra_label": "cillamente|tienen|un|muy|buen|-"}, {"label": "word", "coordinates": {"x": 376.0, "y": 1319.0, "width": 566.0, "height": 120.0}, "extra_label": "cillamente"}, {"label": "word", "coordinates": {"x": 977.0, "y": 1319.0, "width": 369.0, "height": 120.0}, "extra_label": "tienen"}, {"label": "word", "coordinates": {"x": 1371.0, "y": 1350.0, "width": 232.0, "height": 89.0}, "extra_label": "un"}, {"label": "word", "coordinates": {"x": 1652.0, "y": 1319.0, "width": 237.0, "height": 120.0}, "extra_label": "muy"}, {"label": "word", "coordinates": {"x": 1919.0, "y": 1319.0, "width": 257.0, "height": 67.0}, "extra_label": "buen"}, {"label": "word", "coordinates": {"x": 2336.324324324324, "y": 1323.3513513513512, "width": 84.0, "height": 49.0}, "extra_label": "-"}, {"label": "line", "coordinates": {"x": 344.3243243243243, "y": 1423.3513513513512, "width": 2084.0, "height": 114.0}, "extra_label": "background|financiero|y|perciben"}, {"label": "word", "coordinates": {"x": 391.0, "y": 1439.0, "width": 687.0, "height": 93.0}, "extra_label": "background"}, {"label": "word", "coordinates": {"x": 1109.3243243243244, "y": 1434.3513513513512, "width": 592.0, "height": 92.0}, "extra_label": "financiero"}, {"label": "word", "coordinates": {"x": 1747.3243243243244, "y": 1451.3513513513512, "width": 54.0, "height": 111.0}, "extra_label": "y"}, {"label": "word", "coordinates": {"x": 1885.0, "y": 1429.3513513513512, "width": 462.32432432432415, "height": 102.64864864864876}, "extra_label": "perciben"}, {"label": "line", "coordinates": {"x": 339.3243243243243, "y": 1518.3513513513512, "width": 2144.3513513513517, "height": 117.64864864864876}, "extra_label": "los|negocios|fraudulentos|,|porque|en|-"}, {"label": "word", "coordinates": {"x": 377.0, "y": 1540.3513513513512, "width": 178.32432432432427, "height": 78.64864864864876}, "extra_label": "los"}, {"label": "word", "coordinates": {"x": 610.0, "y": 1534.3513513513512, "width": 464.3243243243244, "height": 101.64864864864876}, "extra_label": "negocios"}, {"label": "word", "coordinates": {"x": 1092.0, "y": 1532.0, "width": 684.3243243243244, "height": 94.35135135135124}, "extra_label": "fraudulentos"}, {"label": "word", "coordinates": {"x": 1809.3243243243244, "y": 1542.3513513513512, "width": 38.0, "height": 41.0}, "extra_label": ","}, {"label": "word", "coordinates": {"x": 1868.3243243243244, "y": 1531.3513513513512, "width": 340.9999999999998, "height": 104.64864864864876}, "extra_label": "porque"}, {"label": "word", "coordinates": {"x": 2258.0, "y": 1532.0, "width": 135.32432432432415, "height": 48.35135135135124}, "extra_label": "en"}, {"label": "word", "coordinates": {"x": 2412.324324324324, "y": 1526.3513513513512, "width": 24.0, "height": 35.0}, "extra_label": "-"}, {"label": "line", "coordinates": {"x": 380.0, "y": 1631.3513513513512, "width": 1984.6756756756758, "height": 158.64864864864876}, "extra_label": "tonces|el|cubano|sigue|invirtiendo|."}, {"label": "word", "coordinates": {"x": 390.0, "y": 1636.0, "width": 334.0, "height": 109.0}, "extra_label": "tonces"}, {"label": "word", "coordinates": {"x": 760.3243243243243, "y": 1636.0, "width": 133.67567567567573, "height": 114.35135135135124}, "extra_label": "el"}, {"label": "word", "coordinates": {"x": 960.0, "y": 1636.0, "width": 402.0, "height": 103.0}, "extra_label": "cubano"}, {"label": "word", "coordinates": {"x": 1381.0, "y": 1643.3513513513512, "width": 321.6756756756756, "height": 134.0}, "extra_label": "sigue"}, {"label": "word", "coordinates": {"x": 1722.0, "y": 1636.3513513513512, "width": 614.3243243243242, "height": 106.64864864864876}, "extra_label": "invirtiendo"}, {"label": "word", "coordinates": {"x": 2341.324324324324, "y": 1685.3513513513512, "width": 19.0, "height": 22.0}, "extra_label": "."}]}]