[{"image": "136-S2-A162.png", "annotations": [{"label": "ID", "coordinates": {"x": 2045.0, "y": 307.0, "width": 254.0, "height": 50.0}, "extra_label": "136-S2-A162"}, {"label": "printed_text", "coordinates": {"x": 298.0, "y": 435.0, "width": 2005.0, "height": 225.0}, "extra_label": ""}, {"label": "handwritten_text", "coordinates": {"x": 93.0, "y": 735.0, "width": 2393.0, "height": 881.0}, "extra_label": ""}, {"label": "line", "coordinates": {"x": 93.0, "y": 735.0, "width": 2393.0, "height": 137.0}, "extra_label": "Las|movilizaciones|en|las|diferentes|provincias|cubanas"}, {"label": "word", "coordinates": {"x": 313.0, "y": 777.0, "width": 137.0, "height": 95.0}, "extra_label": "Las"}, {"label": "word", "coordinates": {"x": 488.0, "y": 772.0, "width": 590.0, "height": 100.0}, "extra_label": "movilizaciones"}, {"label": "word", "coordinates": {"x": 1086.0, "y": 806.0, "width": 120.0, "height": 54.0}, "extra_label": "en"}, {"label": "word", "coordinates": {"x": 1231.7567567567567, "y": 778.0, "width": 130.0, "height": 79.0}, "extra_label": "las"}, {"label": "word", "coordinates": {"x": 1374.7567567567567, "y": 757.0, "width": 354.0, "height": 105.0}, "extra_label": "diferentes"}, {"label": "word", "coordinates": {"x": 1745.7567567567567, "y": 770.0, "width": 383.0, "height": 92.0}, "extra_label": "provincias"}, {"label": "word", "coordinates": {"x": 2162.0, "y": 756.0, "width": 291.0, "height": 91.0}, "extra_label": "cubanas"}, {"label": "line", "coordinates": {"x": 93.0, "y": 872.0, "width": 2393.0, "height": 108.0}, "extra_label": "estan|tambi\u00e9n|dedicadas|a|recordar|a|Ch\u00e1vez|y|a|respaldar"}, {"label": "word", "coordinates": {"x": 126.0, "y": 892.0, "width": 181.75675675675677, "height": 88.0}, "extra_label": "estan"}, {"label": "word", "coordinates": {"x": 367.0, "y": 872.0, "width": 320.0, "height": 108.0}, "extra_label": "tambi\u00e9n"}, {"label": "word", "coordinates": {"x": 712.0, "y": 872.0, "width": 395.0, "height": 108.0}, "extra_label": "dedicadas"}, {"label": "word", "coordinates": {"x": 1127.0, "y": 914.0, "width": 63.0, "height": 66.0}, "extra_label": "a"}, {"label": "word", "coordinates": {"x": 1206.0, "y": 872.0, "width": 333.0, "height": 108.0}, "extra_label": "recordar"}, {"label": "word", "coordinates": {"x": 1551.0, "y": 905.0, "width": 63.0, "height": 75.0}, "extra_label": "a"}, {"label": "word", "coordinates": {"x": 1651.0, "y": 872.0, "width": 258.0, "height": 108.0}, "extra_label": "Ch\u00e1vez"}, {"label": "word", "coordinates": {"x": 1928.7567567567567, "y": 914.0, "width": 81.0, "height": 59.0}, "extra_label": "y"}, {"label": "word", "coordinates": {"x": 2023.7567567567567, "y": 916.0, "width": 57.0, "height": 52.0}, "extra_label": "a"}, {"label": "word", "coordinates": {"x": 2104.0, "y": 872.0, "width": 353.0, "height": 108.0}, "extra_label": "respaldar"}, {"label": "line", "coordinates": {"x": 93.0, "y": 980.0, "width": 2393.0, "height": 104.0}, "extra_label": "a|la|Revoluci\u00f3n|Bolivariana|que|lider\u00f3|,|hasta|su|muerte"}, {"label": "word", "coordinates": {"x": 126.75675675675674, "y": 1019.0, "width": 54.0, "height": 57.0}, "extra_label": "a"}, {"label": "word", "coordinates": {"x": 182.75675675675674, "y": 1003.0, "width": 100.00000000000003, "height": 75.0}, "extra_label": "la"}, {"label": "word", "coordinates": {"x": 317.0, "y": 980.0, "width": 437.0, "height": 104.0}, "extra_label": "Revoluci\u00f3n"}, {"label": "word", "coordinates": {"x": 783.0, "y": 980.0, "width": 480.75675675675666, "height": 101.0}, "extra_label": "Bolivariana"}, {"label": "word", "coordinates": {"x": 1277.7567567567567, "y": 1011.0, "width": 159.0, "height": 73.0}, "extra_label": "que"}, {"label": "word", "coordinates": {"x": 1434.7567567567567, "y": 981.0, "width": 262.0, "height": 95.0}, "extra_label": "lider\u00f3"}, {"label": "word", "coordinates": {"x": 1693.7567567567567, "y": 1046.0, "width": 33.0, "height": 32.0}, "extra_label": ","}, {"label": "word", "coordinates": {"x": 1742.0, "y": 1000.0, "width": 246.75675675675666, "height": 84.0}, "extra_label": "hasta"}, {"label": "word", "coordinates": {"x": 2021.0, "y": 1022.0, "width": 128.0, "height": 62.0}, "extra_label": "su"}, {"label": "word", "coordinates": {"x": 2179.0, "y": 1001.0, "width": 286.0, "height": 83.0}, "extra_label": "muerte"}, {"label": "line", "coordinates": {"x": 93.0, "y": 1084.0, "width": 2393.0, "height": 91.0}, "extra_label": "el|pasado|5|de|marzo|.|Seg\u00fan|la|Central|de|Trabajadores"}, {"label": "word", "coordinates": {"x": 135.0, "y": 1109.0, "width": 74.0, "height": 66.0}, "extra_label": "el"}, {"label": "word", "coordinates": {"x": 251.0, "y": 1113.0, "width": 262.0, "height": 62.0}, "extra_label": "pasado"}, {"label": "word", "coordinates": {"x": 550.0, "y": 1113.0, "width": 50.0, "height": 62.0}, "extra_label": "5"}, {"label": "word", "coordinates": {"x": 616.0, "y": 1096.0, "width": 96.0, "height": 79.0}, "extra_label": "de"}, {"label": "word", "coordinates": {"x": 754.0, "y": 1084.0, "width": 253.0, "height": 91.0}, "extra_label": "marzo"}, {"label": "word", "coordinates": {"x": 1004.7567567567568, "y": 1124.0, "width": 26.999999999999886, "height": 33.0}, "extra_label": "."}, {"label": "word", "coordinates": {"x": 1036.0, "y": 1084.0, "width": 283.0, "height": 91.0}, "extra_label": "Seg\u00fan"}, {"label": "word", "coordinates": {"x": 1319.0, "y": 1084.0, "width": 116.0, "height": 91.0}, "extra_label": "la"}, {"label": "word", "coordinates": {"x": 1489.0, "y": 1084.0, "width": 282.0, "height": 91.0}, "extra_label": "Central"}, {"label": "word", "coordinates": {"x": 1805.0, "y": 1109.0, "width": 87.0, "height": 66.0}, "extra_label": "de"}, {"label": "word", "coordinates": {"x": 1929.0, "y": 1096.0, "width": 491.0, "height": 79.0}, "extra_label": "Trabajadores"}, {"label": "line", "coordinates": {"x": 93.75675675675674, "y": 1175.0, "width": 2392.2432432432433, "height": 130.0}, "extra_label": "de|Cuba|,|m\u00e1s|de|dos|mil|dirigentes|sindicales|,|activistas"}, {"label": "word", "coordinates": {"x": 131.75675675675674, "y": 1238.0, "width": 81.24324324324326, "height": 70.0}, "extra_label": "de"}, {"label": "word", "coordinates": {"x": 238.0, "y": 1222.0, "width": 179.75675675675677, "height": 78.0}, "extra_label": "Cuba"}, {"label": "word", "coordinates": {"x": 445.7567567567568, "y": 1270.0, "width": 29.0, "height": 46.0}, "extra_label": ","}, {"label": "word", "coordinates": {"x": 500.0, "y": 1188.0, "width": 158.0, "height": 100.0}, "extra_label": "m\u00e1s"}, {"label": "word", "coordinates": {"x": 695.0, "y": 1196.0, "width": 92.0, "height": 92.0}, "extra_label": "de"}, {"label": "word", "coordinates": {"x": 803.0, "y": 1175.0, "width": 154.0, "height": 96.0}, "extra_label": "dos"}, {"label": "word", "coordinates": {"x": 978.0, "y": 1184.0, "width": 164.75675675675666, "height": 79.0}, "extra_label": "mil"}, {"label": "word", "coordinates": {"x": 1190.0, "y": 1175.0, "width": 394.0, "height": 113.0}, "extra_label": "dirigentes"}, {"label": "word", "coordinates": {"x": 1593.0, "y": 1175.0, "width": 395.75675675675666, "height": 109.0}, "extra_label": "sindicales"}, {"label": "word", "coordinates": {"x": 2001.7567567567567, "y": 1251.0, "width": 27.0, "height": 41.0}, "extra_label": ","}, {"label": "word", "coordinates": {"x": 2046.0, "y": 1200.0, "width": 361.75675675675666, "height": 88.0}, "extra_label": "activistas"}, {"label": "line", "coordinates": {"x": 88.75675675675674, "y": 1300.0, "width": 2392.0, "height": 141.0}, "extra_label": "sociales|y|de|solidaridad|de|73|pa\u00edses|participan|en|los"}, {"label": "word", "coordinates": {"x": 135.0, "y": 1325.0, "width": 295.0, "height": 100.0}, "extra_label": "sociales"}, {"label": "word", "coordinates": {"x": 463.0, "y": 1366.0, "width": 87.0, "height": 75.0}, "extra_label": "y"}, {"label": "word", "coordinates": {"x": 567.0, "y": 1333.0, "width": 79.0, "height": 71.0}, "extra_label": "de"}, {"label": "word", "coordinates": {"x": 679.0, "y": 1314.0, "width": 476.75675675675666, "height": 82.0}, "extra_label": "solidaridad"}, {"label": "word", "coordinates": {"x": 1215.0, "y": 1308.0, "width": 99.0, "height": 75.0}, "extra_label": "de"}, {"label": "word", "coordinates": {"x": 1369.7567567567567, "y": 1311.0, "width": 92.0, "height": 59.0}, "extra_label": "73"}, {"label": "word", "coordinates": {"x": 1488.7567567567567, "y": 1303.0, "width": 259.0, "height": 105.0}, "extra_label": "paises"}, {"label": "word", "coordinates": {"x": 1767.0, "y": 1311.0, "width": 440.75675675675666, "height": 118.0}, "extra_label": "participan"}, {"label": "word", "coordinates": {"x": 2236.7567567567567, "y": 1341.0, "width": 103.0, "height": 62.0}, "extra_label": "en"}, {"label": "word", "coordinates": {"x": 2334.7567567567567, "y": 1322.0, "width": 146.0, "height": 81.0}, "extra_label": "los"}, {"label": "line", "coordinates": {"x": 93.0, "y": 1441.0, "width": 436.0, "height": 175.0}, "extra_label": "festejos|."}, {"label": "word", "coordinates": {"x": 122.0, "y": 1441.0, "width": 266.0, "height": 175.0}, "extra_label": "festejos"}, {"label": "word", "coordinates": {"x": 396.7567567567568, "y": 1500.0, "width": 21.0, "height": 35.0}, "extra_label": "."}]}]