[{"image": "234-S1-D121.png", "annotations": [{"label": "ID", "coordinates": {"x": 2047.0, "y": 321.0, "width": 256.0, "height": 52.0}, "extra_label": "234-S1-D121"}, {"label": "printed_text", "coordinates": {"x": 303.0, "y": 428.0, "width": 2006.0, "height": 238.0}, "extra_label": ""}, {"label": "handwritten_text", "coordinates": {"x": 265.0, "y": 746.0, "width": 2065.0, "height": 1092.0}, "extra_label": ""}, {"label": "line", "coordinates": {"x": 265.0, "y": 746.0, "width": 2065.0, "height": 125.0}, "extra_label": "Han|pasado|casi|cuatro|a\u00f1os|desde|que|te|fuiste|,"}, {"label": "word", "coordinates": {"x": 315.0, "y": 746.0, "width": 151.0, "height": 108.0}, "extra_label": "Han"}, {"label": "word", "coordinates": {"x": 480.0, "y": 782.0, "width": 269.0, "height": 89.0}, "extra_label": "pasado"}, {"label": "word", "coordinates": {"x": 763.0, "y": 781.0, "width": 178.21621621621625, "height": 81.0}, "extra_label": "casi"}, {"label": "word", "coordinates": {"x": 961.0, "y": 771.0, "width": 240.0, "height": 90.0}, "extra_label": "cuatro"}, {"label": "word", "coordinates": {"x": 1229.0, "y": 771.0, "width": 194.0, "height": 83.0}, "extra_label": "a\u00f1os"}, {"label": "word", "coordinates": {"x": 1444.0, "y": 768.0, "width": 237.0, "height": 86.0}, "extra_label": "desde"}, {"label": "word", "coordinates": {"x": 1703.0, "y": 785.0, "width": 150.0, "height": 86.0}, "extra_label": "que"}, {"label": "word", "coordinates": {"x": 1889.0, "y": 757.0, "width": 75.0, "height": 86.0}, "extra_label": "te"}, {"label": "word", "coordinates": {"x": 1975.0, "y": 757.0, "width": 258.0, "height": 114.0}, "extra_label": "fuiste"}, {"label": "word", "coordinates": {"x": 2240.0, "y": 818.0, "width": 29.0, "height": 36.0}, "extra_label": ","}, {"label": "line", "coordinates": {"x": 265.0, "y": 871.0, "width": 2065.0, "height": 108.0}, "extra_label": "y|como|era|muy|peque\u00f1o|y|no|tuvimos|mucho"}, {"label": "word", "coordinates": {"x": 312.0, "y": 900.0, "width": 53.0, "height": 79.0}, "extra_label": "y"}, {"label": "word", "coordinates": {"x": 380.0, "y": 900.0, "width": 183.0, "height": 65.0}, "extra_label": "como"}, {"label": "word", "coordinates": {"x": 595.0, "y": 904.0, "width": 129.0, "height": 64.0}, "extra_label": "era"}, {"label": "word", "coordinates": {"x": 763.0, "y": 907.0, "width": 176.0, "height": 72.0}, "extra_label": "muy"}, {"label": "word", "coordinates": {"x": 986.0, "y": 871.0, "width": 337.0, "height": 108.0}, "extra_label": "peque\u00f1o"}, {"label": "word", "coordinates": {"x": 1366.0, "y": 900.0, "width": 50.0, "height": 79.0}, "extra_label": "y"}, {"label": "word", "coordinates": {"x": 1444.0, "y": 897.0, "width": 104.0, "height": 50.0}, "extra_label": "no"}, {"label": "word", "coordinates": {"x": 1570.0, "y": 871.0, "width": 315.0, "height": 87.0}, "extra_label": "tuvimos"}, {"label": "word", "coordinates": {"x": 1943.0, "y": 871.0, "width": 272.0, "height": 79.0}, "extra_label": "mucho"}, {"label": "line", "coordinates": {"x": 265.0, "y": 979.0, "width": 2065.0, "height": 122.0}, "extra_label": "tiempo|para|hablar|,|me|gustar\u00eda|contarte|que"}, {"label": "word", "coordinates": {"x": 287.0, "y": 979.0, "width": 286.0, "height": 122.0}, "extra_label": "tiempo"}, {"label": "word", "coordinates": {"x": 609.0, "y": 1018.0, "width": 187.0, "height": 83.0}, "extra_label": "para"}, {"label": "word", "coordinates": {"x": 831.0, "y": 979.0, "width": 259.0, "height": 100.0}, "extra_label": "hablar"}, {"label": "word", "coordinates": {"x": 1125.0, "y": 1036.0, "width": 33.0, "height": 47.0}, "extra_label": ","}, {"label": "word", "coordinates": {"x": 1176.0, "y": 1011.0, "width": 114.0, "height": 58.0}, "extra_label": "me"}, {"label": "word", "coordinates": {"x": 1326.0, "y": 979.0, "width": 337.0, "height": 122.0}, "extra_label": "gustar\u00eda"}, {"label": "word", "coordinates": {"x": 1703.0, "y": 979.0, "width": 315.0, "height": 93.0}, "extra_label": "contarte"}, {"label": "word", "coordinates": {"x": 2058.0, "y": 997.0, "width": 175.0, "height": 104.0}, "extra_label": "que"}, {"label": "line", "coordinates": {"x": 265.0, "y": 1101.0, "width": 2065.0, "height": 118.0}, "extra_label": "nuestra|familia|sigue|muy|unida|y|creciendo"}, {"label": "word", "coordinates": {"x": 290.0, "y": 1101.0, "width": 312.0, "height": 118.0}, "extra_label": "nuestra"}, {"label": "word", "coordinates": {"x": 634.0, "y": 1101.0, "width": 319.0, "height": 118.0}, "extra_label": "familia"}, {"label": "word", "coordinates": {"x": 996.0, "y": 1114.0, "width": 248.21621621621625, "height": 105.0}, "extra_label": "sigue"}, {"label": "word", "coordinates": {"x": 1297.0, "y": 1140.0, "width": 198.0, "height": 79.0}, "extra_label": "muy"}, {"label": "word", "coordinates": {"x": 1534.0, "y": 1101.0, "width": 262.0, "height": 100.0}, "extra_label": "unida"}, {"label": "word", "coordinates": {"x": 1832.0, "y": 1133.0, "width": 53.0, "height": 86.0}, "extra_label": "y"}, {"label": "word", "coordinates": {"x": 1932.0, "y": 1101.0, "width": 355.0, "height": 82.0}, "extra_label": "creciendo"}, {"label": "line", "coordinates": {"x": 265.0, "y": 1219.0, "width": 2065.0, "height": 108.0}, "extra_label": "con|mucho|esfuerzo|y|cari\u00f1o|.|Nos|gusta|estar"}, {"label": "word", "coordinates": {"x": 301.0, "y": 1259.0, "width": 136.0, "height": 68.0}, "extra_label": "con"}, {"label": "word", "coordinates": {"x": 487.0, "y": 1219.0, "width": 305.0, "height": 93.0}, "extra_label": "mucho"}, {"label": "word", "coordinates": {"x": 846.0, "y": 1219.0, "width": 330.0, "height": 108.0}, "extra_label": "esfuerzo"}, {"label": "word", "coordinates": {"x": 1219.0, "y": 1237.0, "width": 53.0, "height": 90.0}, "extra_label": "y"}, {"label": "word", "coordinates": {"x": 1290.0, "y": 1219.0, "width": 248.0, "height": 86.0}, "extra_label": "cari\u00f1o"}, {"label": "word", "coordinates": {"x": 1557.2162162162163, "y": 1265.0, "width": 25.0, "height": 32.0}, "extra_label": "."}, {"label": "word", "coordinates": {"x": 1617.0, "y": 1219.0, "width": 150.0, "height": 86.0}, "extra_label": "Nos"}, {"label": "word", "coordinates": {"x": 1825.0, "y": 1219.0, "width": 236.0, "height": 108.0}, "extra_label": "gusta"}, {"label": "word", "coordinates": {"x": 2108.0, "y": 1219.0, "width": 208.0, "height": 86.0}, "extra_label": "estar"}, {"label": "line", "coordinates": {"x": 265.0, "y": 1327.0, "width": 2065.0, "height": 111.0}, "extra_label": "juntos|y|compartir|nuestros|juegos|,|pero|sobre"}, {"label": "word", "coordinates": {"x": 292.2162162162162, "y": 1352.0, "width": 252.7837837837838, "height": 113.0}, "extra_label": "juntos"}, {"label": "word", "coordinates": {"x": 595.0, "y": 1370.0, "width": 54.0, "height": 68.0}, "extra_label": "y"}, {"label": "word", "coordinates": {"x": 670.0, "y": 1327.0, "width": 416.0, "height": 111.0}, "extra_label": "compartir"}, {"label": "word", "coordinates": {"x": 1133.0, "y": 1345.0, "width": 315.0, "height": 93.0}, "extra_label": "nuestros"}, {"label": "word", "coordinates": {"x": 1470.0, "y": 1359.0, "width": 251.0, "height": 79.0}, "extra_label": "juegos"}, {"label": "word", "coordinates": {"x": 1756.0, "y": 1388.0, "width": 33.0, "height": 50.0}, "extra_label": ","}, {"label": "word", "coordinates": {"x": 1814.0, "y": 1355.0, "width": 175.0, "height": 83.0}, "extra_label": "pero"}, {"label": "word", "coordinates": {"x": 2018.0, "y": 1327.0, "width": 230.0, "height": 82.0}, "extra_label": "sobre"}, {"label": "line", "coordinates": {"x": 265.0, "y": 1438.0, "width": 2065.0, "height": 122.0}, "extra_label": "todo|procuramos|estar|unidos|y|contentos"}, {"label": "word", "coordinates": {"x": 283.0, "y": 1470.0, "width": 209.2162162162162, "height": 87.0}, "extra_label": "todo"}, {"label": "word", "coordinates": {"x": 545.0, "y": 1477.0, "width": 512.0, "height": 83.0}, "extra_label": "procuramos"}, {"label": "word", "coordinates": {"x": 1118.0, "y": 1449.0, "width": 223.0, "height": 100.0}, "extra_label": "estar"}, {"label": "word", "coordinates": {"x": 1409.0, "y": 1438.0, "width": 308.0, "height": 104.0}, "extra_label": "unidos"}, {"label": "word", "coordinates": {"x": 1778.0, "y": 1488.0, "width": 54.0, "height": 72.0}, "extra_label": "y"}, {"label": "word", "coordinates": {"x": 1864.0, "y": 1438.0, "width": 401.0, "height": 97.0}, "extra_label": "contentos"}, {"label": "line", "coordinates": {"x": 265.0, "y": 1560.0, "width": 2065.0, "height": 154.0}, "extra_label": "porque|estamos|sanos|y|por|todo|lo|que"}, {"label": "word", "coordinates": {"x": 294.0, "y": 1617.0, "width": 283.0, "height": 97.0}, "extra_label": "porque"}, {"label": "word", "coordinates": {"x": 624.0, "y": 1571.0, "width": 319.0, "height": 93.0}, "extra_label": "estamos"}, {"label": "word", "coordinates": {"x": 1004.0, "y": 1592.0, "width": 243.0, "height": 61.0}, "extra_label": "sanos"}, {"label": "word", "coordinates": {"x": 1308.0, "y": 1603.0, "width": 50.0, "height": 93.0}, "extra_label": "y"}, {"label": "word", "coordinates": {"x": 1387.0, "y": 1585.0, "width": 165.0, "height": 86.0}, "extra_label": "por"}, {"label": "word", "coordinates": {"x": 1581.0, "y": 1560.0, "width": 200.0, "height": 93.0}, "extra_label": "todo"}, {"label": "word", "coordinates": {"x": 1827.2162162162163, "y": 1568.0, "width": 79.0, "height": 83.0}, "extra_label": "lo"}, {"label": "word", "coordinates": {"x": 1930.2162162162163, "y": 1571.0, "width": 177.78378378378375, "height": 113.0}, "extra_label": "que"}, {"label": "line", "coordinates": {"x": 265.0, "y": 1714.0, "width": 437.0, "height": 122.0}, "extra_label": "tenemos|."}, {"label": "word", "coordinates": {"x": 283.0, "y": 1714.0, "width": 376.0, "height": 93.0}, "extra_label": "tenemos"}, {"label": "word", "coordinates": {"x": 674.0, "y": 1761.0, "width": 28.0, "height": 28.0}, "extra_label": "."}]}]