[{"image": "337-S1-C158.png", "annotations": [{"label": "ID", "coordinates": {"x": 2107.0, "y": 379.0, "width": 253.0, "height": 41.0}, "extra_label": "337-S1-C158"}, {"label": "printed_text", "coordinates": {"x": 355.0, "y": 429.0, "width": 2017.0, "height": 256.0}, "extra_label": ""}, {"label": "handwritten_text", "coordinates": {"x": 331.0, "y": 848.0, "width": 2219.0, "height": 1308.0}, "extra_label": ""}, {"label": "line", "coordinates": {"x": 331.0, "y": 878.0, "width": 2219.0, "height": 154.0}, "extra_label": "Tales|documentos|que|nosotros|poseemos|nos|retroceden"}, {"label": "word", "coordinates": {"x": 341.0, "y": 878.0, "width": 212.0, "height": 108.0}, "extra_label": "Tales"}, {"label": "word", "coordinates": {"x": 589.0, "y": 907.0, "width": 459.0, "height": 77.0}, "extra_label": "documentos"}, {"label": "word", "coordinates": {"x": 1089.0, "y": 944.0, "width": 168.0, "height": 88.0}, "extra_label": "que"}, {"label": "word", "coordinates": {"x": 1303.0, "y": 924.0, "width": 306.0, "height": 70.0}, "extra_label": "nosotros"}, {"label": "word", "coordinates": {"x": 1629.0, "y": 947.0, "width": 343.0, "height": 85.0}, "extra_label": "poseemos"}, {"label": "word", "coordinates": {"x": 2006.0, "y": 947.0, "width": 133.0, "height": 28.0}, "extra_label": "nos"}, {"label": "word", "coordinates": {"x": 2158.0, "y": 915.0, "width": 294.0, "height": 65.0}, "extra_label": "retroceden"}, {"label": "line", "coordinates": {"x": 375.0, "y": 1062.0, "width": 1819.0, "height": 156.0}, "extra_label": "solamente|hasta|el|fin|del|siglo|XVIII|o"}, {"label": "word", "coordinates": {"x": 385.0, "y": 1077.0, "width": 347.0, "height": 63.0}, "extra_label": "solamente"}, {"label": "word", "coordinates": {"x": 791.0, "y": 1062.0, "width": 231.0, "height": 89.0}, "extra_label": "hasta"}, {"label": "word", "coordinates": {"x": 1093.0, "y": 1062.0, "width": 131.0, "height": 90.0}, "extra_label": "el"}, {"label": "word", "coordinates": {"x": 1253.0, "y": 1090.0, "width": 143.0, "height": 98.0}, "extra_label": "fin"}, {"label": "word", "coordinates": {"x": 1452.0, "y": 1076.0, "width": 155.0, "height": 83.0}, "extra_label": "del"}, {"label": "word", "coordinates": {"x": 1669.0, "y": 1062.0, "width": 207.0, "height": 126.0}, "extra_label": "siglo"}, {"label": "word", "coordinates": {"x": 1918.0, "y": 1065.0, "width": 189.32432432432415, "height": 76.0}, "extra_label": "XVIII"}, {"label": "word", "coordinates": {"x": 2142.0, "y": 1104.0, "width": 42.0, "height": 40.0}, "extra_label": "o"}, {"label": "line", "coordinates": {"x": 366.0, "y": 1188.0, "width": 2112.0, "height": 157.0}, "extra_label": "los|principios|del|XIX|.|Se|han|hecho|varias|especula|-"}, {"label": "word", "coordinates": {"x": 376.0, "y": 1229.0, "width": 104.0, "height": 61.0}, "extra_label": "los"}, {"label": "word", "coordinates": {"x": 511.0, "y": 1235.0, "width": 352.0, "height": 110.0}, "extra_label": "principios"}, {"label": "word", "coordinates": {"x": 899.0, "y": 1227.0, "width": 141.0, "height": 70.0}, "extra_label": "del"}, {"label": "word", "coordinates": {"x": 1090.0, "y": 1229.0, "width": 132.0, "height": 71.0}, "extra_label": "XIX"}, {"label": "word", "coordinates": {"x": 1237.0, "y": 1278.0, "width": 25.0, "height": 21.0}, "extra_label": "."}, {"label": "word", "coordinates": {"x": 1282.0, "y": 1226.0, "width": 111.0, "height": 69.0}, "extra_label": "Se"}, {"label": "word", "coordinates": {"x": 1422.0, "y": 1223.0, "width": 141.0, "height": 73.0}, "extra_label": "han"}, {"label": "word", "coordinates": {"x": 1619.0, "y": 1188.0, "width": 228.0, "height": 97.0}, "extra_label": "hecho"}, {"label": "word", "coordinates": {"x": 1890.0, "y": 1219.0, "width": 248.0, "height": 68.0}, "extra_label": "varias"}, {"label": "word", "coordinates": {"x": 2168.0, "y": 1188.0, "width": 274.32432432432415, "height": 155.0}, "extra_label": "especula"}, {"label": "word", "coordinates": {"x": 2442.324324324324, "y": 1243.0, "width": 25.0, "height": 25.0}, "extra_label": "-"}, {"label": "line", "coordinates": {"x": 384.0, "y": 1363.0, "width": 1921.0, "height": 143.0}, "extra_label": "ciones|,|varias|teor\u00edas|han|sido|presentadas|por"}, {"label": "word", "coordinates": {"x": 394.0, "y": 1387.0, "width": 208.0, "height": 55.0}, "extra_label": "ciones"}, {"label": "word", "coordinates": {"x": 616.0, "y": 1428.0, "width": 25.0, "height": 43.0}, "extra_label": ","}, {"label": "word", "coordinates": {"x": 668.0, "y": 1378.0, "width": 231.32432432432438, "height": 63.0}, "extra_label": "varias"}, {"label": "word", "coordinates": {"x": 902.3243243243244, "y": 1378.0, "width": 297.0, "height": 65.0}, "extra_label": "teor\u00edas"}, {"label": "word", "coordinates": {"x": 1256.0, "y": 1363.0, "width": 157.0, "height": 76.0}, "extra_label": "han"}, {"label": "word", "coordinates": {"x": 1458.0, "y": 1382.0, "width": 186.0, "height": 66.0}, "extra_label": "sido"}, {"label": "word", "coordinates": {"x": 1721.0, "y": 1376.0, "width": 430.0, "height": 112.0}, "extra_label": "presentadas"}, {"label": "word", "coordinates": {"x": 2167.0, "y": 1416.0, "width": 128.0, "height": 72.0}, "extra_label": "por"}, {"label": "line", "coordinates": {"x": 378.0, "y": 1515.0, "width": 1862.0, "height": 150.0}, "extra_label": "diferentes|escritores|,|pero|ninguno|ha|tenido"}, {"label": "word", "coordinates": {"x": 388.0, "y": 1515.0, "width": 359.0, "height": 123.0}, "extra_label": "diferentes"}, {"label": "word", "coordinates": {"x": 795.0, "y": 1515.0, "width": 357.0, "height": 94.0}, "extra_label": "escritores"}, {"label": "word", "coordinates": {"x": 1173.0, "y": 1573.0, "width": 16.0, "height": 50.0}, "extra_label": ","}, {"label": "word", "coordinates": {"x": 1213.0, "y": 1563.0, "width": 177.0, "height": 75.0}, "extra_label": "pero"}, {"label": "word", "coordinates": {"x": 1423.0, "y": 1536.0, "width": 301.0, "height": 102.0}, "extra_label": "ninguno"}, {"label": "word", "coordinates": {"x": 1754.0, "y": 1515.0, "width": 122.0, "height": 83.0}, "extra_label": "ha"}, {"label": "word", "coordinates": {"x": 1908.0, "y": 1532.0, "width": 322.0, "height": 69.0}, "extra_label": "tenido"}, {"label": "line", "coordinates": {"x": 342.0, "y": 1663.0, "width": 1991.0, "height": 155.0}, "extra_label": "todav\u00eda|exito|en|identificar|la|localidad"}, {"label": "word", "coordinates": {"x": 352.0, "y": 1663.0, "width": 366.0, "height": 76.0}, "extra_label": "todav\u00eda"}, {"label": "word", "coordinates": {"x": 781.0, "y": 1663.0, "width": 210.0, "height": 82.0}, "extra_label": "exito"}, {"label": "word", "coordinates": {"x": 1048.0, "y": 1714.0, "width": 107.0, "height": 31.0}, "extra_label": "en"}, {"label": "word", "coordinates": {"x": 1210.0, "y": 1673.0, "width": 478.3243243243244, "height": 120.0}, "extra_label": "identificar"}, {"label": "word", "coordinates": {"x": 1743.0, "y": 1663.0, "width": 120.0, "height": 91.0}, "extra_label": "la"}, {"label": "word", "coordinates": {"x": 1911.0, "y": 1663.0, "width": 412.0, "height": 85.0}, "extra_label": "localidad"}, {"label": "line", "coordinates": {"x": 371.0, "y": 1793.0, "width": 2133.324324324324, "height": 131.0}, "extra_label": "para|establecer|una|conexi\u00f3n|entre|esa|localidad"}, {"label": "word", "coordinates": {"x": 381.0, "y": 1854.0, "width": 180.0, "height": 75.0}, "extra_label": "para"}, {"label": "word", "coordinates": {"x": 601.0, "y": 1830.0, "width": 413.0, "height": 80.0}, "extra_label": "establecer"}, {"label": "word", "coordinates": {"x": 1070.0, "y": 1850.0, "width": 167.0, "height": 45.0}, "extra_label": "una"}, {"label": "word", "coordinates": {"x": 1279.0, "y": 1831.0, "width": 318.0, "height": 75.0}, "extra_label": "conexi\u00f3n"}, {"label": "word", "coordinates": {"x": 1643.0, "y": 1835.0, "width": 200.0, "height": 72.0}, "extra_label": "entre"}, {"label": "word", "coordinates": {"x": 1878.0, "y": 1859.0, "width": 149.0, "height": 38.0}, "extra_label": "esa"}, {"label": "word", "coordinates": {"x": 2071.0, "y": 1812.0, "width": 395.0, "height": 83.0}, "extra_label": "localidad"}, {"label": "line", "coordinates": {"x": 391.0, "y": 1961.0, "width": 949.0, "height": 178.0}, "extra_label": "y|la|religion|Yoruba"}, {"label": "word", "coordinates": {"x": 401.0, "y": 2023.0, "width": 42.0, "height": 101.0}, "extra_label": "y"}, {"label": "word", "coordinates": {"x": 462.0, "y": 1980.0, "width": 125.0, "height": 73.0}, "extra_label": "la"}, {"label": "word", "coordinates": {"x": 609.0, "y": 1983.0, "width": 350.0, "height": 141.0}, "extra_label": "religion"}, {"label": "word", "coordinates": {"x": 1031.0, "y": 1961.0, "width": 299.0, "height": 93.0}, "extra_label": "Yoruba"}]}]